MANIFEST.in
README.rst
setup.py
leven/__init__.py
leven/_levenshtein.cpp
leven/levenshtein_impl.h
leven/levenshtein_types.h
leven.egg-info/PKG-INFO
leven.egg-info/SOURCES.txt
leven.egg-info/dependency_links.txt
leven.egg-info/requires.txt
leven.egg-info/top_level.txt