Metadata-Version: 1.0
Name: leven
Version: 1.0.4
Summary: Levenshtein edit distance library
Home-page: https://github.com/semanticize/leven
Author: Lars Buitinck
Author-email: l.j.buitinck@esciencecenter.nl
License: UNKNOWN
Platform: UNKNOWN
